jenkins_mcp_server/__init__.py
jenkins_mcp_server/__main__.py
jenkins_mcp_server/config.py
jenkins_mcp_server/jenkins_client.py
jenkins_mcp_server/server.py
jenkins_mcp_server-0.1.6.dist-info/METADATA
jenkins_mcp_server-0.1.6.dist-info/WHEEL
jenkins_mcp_server-0.1.6.dist-info/entry_points.txt
jenkins_mcp_server-0.1.6.dist-info/licenses/LICENSE
jenkins_mcp_server-0.1.6.dist-info/RECORD
