Metadata-Version: 2.4
Name: jenkins-mcp-server
Version: 0.1.6
Summary: A Python-based Jenkins MCP server using the Model Context Protocol Python SDK
Project-URL: Homepage, https://github.com/akhilthomas236/jenkins-mcp-server
Project-URL: Issues, https://github.com/akhilthomas236/jenkins-mcp-server/issues
Project-URL: Source, https://github.com/akhilthomas236/jenkins-mcp-server
Author-email: akhilthomas236 <akhilthomas236@gmail.com>
License-File: LICENSE
Requires-Python: >=3.12
Requires-Dist: mcp>=1.9.3
Requires-Dist: pydantic>=2.0.0
Requires-Dist: python-dotenv
Requires-Dist: requests>=2.31.0
Requires-Dist: urllib3>=2.0.0
